CHANGES.md
MANIFEST.in
README.md
setup.py
django_terra_accounts.egg-info/PKG-INFO
django_terra_accounts.egg-info/SOURCES.txt
django_terra_accounts.egg-info/dependency_links.txt
django_terra_accounts.egg-info/requires.txt
django_terra_accounts.egg-info/top_level.txt
terra_accounts/VERSION.md
terra_accounts/__init__.py
terra_accounts/admin.py
terra_accounts/apps.py
terra_accounts/filters.py
terra_accounts/forms.py
terra_accounts/jwt_payload.py
terra_accounts/managers.py
terra_accounts/mixins.py
terra_accounts/models.py
terra_accounts/permissions.py
terra_accounts/permissions_mixins.py
terra_accounts/serializers.py
terra_accounts/signals.py
terra_accounts/urls.py
terra_accounts/views.py
terra_accounts/locale/fr/LC_MESSAGES/django.mo
terra_accounts/migrations/0001_initial.py
terra_accounts/migrations/0002_auto_20180911_0818.py
terra_accounts/migrations/0003_auto_20181023_1522.py
terra_accounts/migrations/0004_auto_20181120_1059.py
terra_accounts/migrations/0005_auto_20190417_1630.py
terra_accounts/migrations/0006_auto_20190912_1336.py
terra_accounts/migrations/0007_terrapermission.py
terra_accounts/migrations/0008_auto_20191025_1041.py
terra_accounts/migrations/0009_terrapermission_module.py
terra_accounts/migrations/0010_auto_20210507_0835.py
terra_accounts/migrations/__init__.py
terra_accounts/templates/registration/accounts_password_reset_email.html
terra_accounts/templates/registration/registration_email.html
terra_accounts/templates/registration/registration_email.txt
terra_accounts/templates/registration/registration_email_subject.txt
terra_accounts/tests/__init__.py
terra_accounts/tests/factories.py